    <addUserObject xmlns="http://ejb3.examples.itko.com/">
      <userObject xmlns="">
        <accounts>
          <balance>127.53</balance>
          <name>Basic Checking</name>
          <type>CHECKING</type>
        </accounts>
        <accounts>
          <balance>129.74</balance>
          <name>Orange Savings</name>
          <type>SAVINGS</type>
        </accounts>
        <addresses>
          <city>Portland</city>
          <line1>Gamma Quadrant.</line1>
          <state>Oregon</state>
          <zip>19073</zip>
        </addresses>
        <addresses>
          <city>Dallas</city>
          <line1>Deep Space Nine</line1>
          <state>Texas</state>
          <zip>75234</zip>
        </addresses>
        <email>Jean.Picard@StarTrekNG.com</email>
        <fname>Jean</fname>
        <lname>Picard</lname>
        <login>{{ds_login}}</login>
        <phone>234-4359</phone>
        <pwd>picard123</pwd>
        <roleKey>REGULAR</roleKey>
      </userObject>
    </addUserObject>